probabilistic_word_embeddings/__init__.py
probabilistic_word_embeddings/data/eval/Card-660.tsv
probabilistic_word_embeddings/data/eval/MC-30.tsv
probabilistic_word_embeddings/data/eval/MEN-TR-3k.tsv
probabilistic_word_embeddings/data/eval/MTurk-287.tsv
probabilistic_word_embeddings/data/eval/MTurk-771.tsv
probabilistic_word_embeddings/data/eval/RG-65.tsv
probabilistic_word_embeddings/data/eval/RW-STANFORD.tsv
probabilistic_word_embeddings/data/eval/SimLex999.tsv
probabilistic_word_embeddings/data/eval/SimVerb-3500.tsv
probabilistic_word_embeddings/data/eval/WS-353-ALL.tsv
probabilistic_word_embeddings/data/eval/WS-353-REL.tsv
probabilistic_word_embeddings/data/eval/WS-353-SIM.tsv
probabilistic_word_embeddings/data/eval/YP-130.tsv
probabilistic_word_embeddings/embeddings.py
probabilistic_word_embeddings/estimation.py
probabilistic_word_embeddings/evaluation.py
probabilistic_word_embeddings/models.py
probabilistic_word_embeddings/preprocessing.py
probabilistic_word_embeddings/utils.py
probabilistic_word_embeddings-1.18.2.dist-info/METADATA
probabilistic_word_embeddings-1.18.2.dist-info/WHEEL
probabilistic_word_embeddings-1.18.2.dist-info/RECORD
