Metadata-Version: 2.1
Name: probabilistic-word-embeddings
Version: 1.18.2
Summary: Probabilistic Word Embeddings for Python
License: MIT
Author: Your Name
Author-email: you@example.com
Requires-Python: >=3.7,<4.0
Classifier: License :: OSI Approved :: MIT License
Classifier: Programming Language :: Python :: 3
Classifier: Programming Language :: Python :: 3.7
Classifier: Programming Language :: Python :: 3.8
Classifier: Programming Language :: Python :: 3.9
Classifier: Programming Language :: Python :: 3.10
Classifier: Programming Language :: Python :: 3.11
Classifier: Programming Language :: Python :: 3.12
Requires-Dist: colorlog
Requires-Dist: networkx
Requires-Dist: pandas
Requires-Dist: progressbar2
Requires-Dist: scikit-learn
Requires-Dist: tensorflow (<=2.15.1)
Requires-Dist: tensorflow-probability (<=0.23)
Project-URL: Documentation, https://ninpnin.github.io/probabilistic-word-embeddings/
